Workbook

Sheet ESTIMATE
A1: SCH-1024 | ROM COST ESTIMATE | LEVEL 3 | FY27 | PAX ID 387356 | Fi Web BU26PPE70M
A3: A. ROM FORMULA CHAIN (live formulas reference PARAMETERS tab)
A4: Step | B4: Element | C4: Amount ($) | D4: Formula / Source
A5: 1 | B5: Base Direct Cost (FY24 CONUS) | C5: =PARAMETERS!B33 | D5: Sum of all scope items on SCOPE_DETAIL
A6: 2 | B6: x ACF 1.85 (Camp Schwab Okinawa) | C6: =C5*1.85 | D6: UFC 3-701-01 w/Ch 7 (25 Jul 2025), Table 4-1
A7: 3 | B7: x Compound Escalation Factor | C7: =C6*PARAMETERS!B32 | D7: OSD FY25 published rate; FY24 to FY27
A8: 4 | B8: x (1 + General Requirements 10%) | C8: =C7*1.10 | D8: FSRM program-directed; UFS 3-740-05
A9: 5 | B9: x Cost Adjustment Factor (calibrated) | C9: =C8*PARAMETERS!B37 | D9: Calibrates ROM chain to locked TPC; absorbs base-cost adjustments
B10: ITEMS SUBTOTAL (PAX Block 9 paste total) | C10: =C9 | D10: Equals Locked TPC / 1.23552
A12: B. PAX ROLLUP VERIFICATION (mirrors what PAX prints on the form)
A13: Step | B13: Element | C13: Amount ($) | D13: Formula / Source
B14: Items Subtotal | C14: =C10 | D14: From Section A
B15: + Contingency (10.0%) PAX-applied | C15: =C10*0.10 | D15: FSRM program-directed
B16: Total Contract Cost | C16: =C10*1.10 | D16: Items Subtotal x 1.10
B17: + SIOH (8.0%) PAX-applied | C17: =C10*1.10*0.08 | D17: OCONUS FSRM customer-directed
B18: Total Funded Cost | C18: =C10*1.10*1.08 | D18: Total Contract Cost x 1.08
B19: + DB Design (4.0%) PAX-applied | C19: =C10*1.10*1.08*0.04 | D19: UFC 3-730-01 (2024)
B20: TOTAL PROJECT COST | C20: =C10*1.23552 | D20: Total Funded Cost x 1.04
B21: TOTAL PROJECT COST ($000 rounded) | C21: =ROUND(C20/1000,0) | D21: Printed face value on DD Form 1391
B22: Locked TPC ($000 rounded) | C22: =ROUND(PARAMETERS!B35/1000,0) | D22: Reconciliation target
B23: Reconciliation (must equal 0) | C23: =C21-C22 | D23: Printed minus Locked
B24: Planning and Design (6.0%) NON ADD | C24: =C10*0.06 | D24: Informational; does not roll into TPC
A26: C. UNIFORMAT II LV2 SUMMARY (Base Direct pre-ACF, by category)
A27: Code | B27: Category | C27: Base Direct ($) | D27: Description
A28: B20 | B28: Exterior Enclosure | C28: =SUMIF(SCOPE_DETAIL!H:H,"B20",SCOPE_DETAIL!G:G) | D28: 2 scope item(s)
A29: C10 | B29: Interior Construction | C29: =SUMIF(SCOPE_DETAIL!H:H,"C10",SCOPE_DETAIL!G:G) | D29: 7 scope item(s)
A30: C30 | B30: Interior Finishes | C30: =SUMIF(SCOPE_DETAIL!H:H,"C30",SCOPE_DETAIL!G:G) | D30: 8 scope item(s)
A31: D20 | B31: Plumbing | C31: =SUMIF(SCOPE_DETAIL!H:H,"D20",SCOPE_DETAIL!G:G) | D31: 6 scope item(s)
A32: D30 | B32: HVAC / Mechanical | C32: =SUMIF(SCOPE_DETAIL!H:H,"D30",SCOPE_DETAIL!G:G) | D32: 8 scope item(s)
A33: D40 | B33: Fire Protection | C33: =SUMIF(SCOPE_DETAIL!H:H,"D40",SCOPE_DETAIL!G:G) | D33: 1 scope item(s)
A34: D50 | B34: Electrical / Communications | C34: =SUMIF(SCOPE_DETAIL!H:H,"D50",SCOPE_DETAIL!G:G) | D34: 11 scope item(s)
A35: E20 | B35: Furnishings | C35: =SUMIF(SCOPE_DETAIL!H:H,"E20",SCOPE_DETAIL!G:G) | D35: 1 scope item(s)
A36: F20 | B36: Selective Demolition | C36: =SUMIF(SCOPE_DETAIL!H:H,"F20",SCOPE_DETAIL!G:G) | D36: 18 scope item(s)
A37: G10 | B37: Site Preparation | C37: =SUMIF(SCOPE_DETAIL!H:H,"G10",SCOPE_DETAIL!G:G) | D37: 1 scope item(s)
A38: G20 | B38: Site Improvements | C38: =SUMIF(SCOPE_DETAIL!H:H,"G20",SCOPE_DETAIL!G:G) | D38: 6 scope item(s)
B39: TOTAL BASE DIRECT (must equal Section A row 5) | C39: =SUM(C28:C38)
A41: D. METHODOLOGY
A42: Estimate Level | B42: Level 3 ROM per UFS 3-740-05 (02 Feb 2026). Non-mandatory supplement; for information only.
A43: Scope Basis | B43: 69 discrete work items across 11 UNIFORMAT II Lv2 categories. Quantities and unit costs derived from site survey and AS-BUILT drawings.
A44: Area Cost Factor | B44: 1.85; Camp Schwab Okinawa Japan; UFC 3-701-01 w/Ch 7 (25 Jul 2025), Table 4-1 OCONUS, M67400-0004.
A45: Escalation | B45: 2.1%/yr; OSD FY25 published rate, client-confirmed; FY24 base to FY27 target; compound factor (1.021)^3 = 1.0643.
A46: General Requirements | B46: 10.0%; FSRM program-directed; UFS 3-740-05.
A47: PAX Associated Costs | B47: Contingency 10%, SIOH 8% (OCONUS FSRM customer-directed), DB Design 4%; combined multiplier 1.23552. Planning and Design 6% NON ADD; informational only.
A48: Cost Adjustment Factor | B48: Live formula in PARAMETERS reconciles the ROM chain to the locked Total Project Cost. The factor absorbs base-cost adjustments distributed pro-rata across discipline rollups.
A49: Unit Cost Basis | B49: FY24 CONUS pre-ACF assembly-level unit costs per RS Means; UFC 3-410-01 / 3-420-01 / 3-520-01 / 3-530-01 / 3-580-01 as applicable.
A50: Items Requiring Verification | B50: JPY/USD exchange rate per Federal Reserve H.10 on date of PAX submission.
A51: Prepared By | B51: Anthony L. Potter | Facilities Planner | MCIPAC G-F PPE | 29 Apr 2026
A53: E. VERSION HISTORY
A54: Version | B54: Date | C54: Total Project Cost ($) | D54: Notes
A55: Current | B55: 29 Apr 2026 | C55: =C20 | D55: 4-tab discipline-rollup architecture; PAX-pasteable Block 9; reconciles to locked TPC

Sheet SCOPE_DETAIL
A1: SCH-1024 | SCOPE DETAIL & QUANTITY TAKEOFF | BASE YEAR FY24 CONUS DIRECT COSTS | Fi Web BU26PPE70M
A2: Yellow = confirmed scope. White = formula-driven extended cost. All unit costs are FY24 CONUS pre-ACF, assembly-level RS Means basis.
A3: Item | B3: Group | C3: Work Description | D3: Qty | E3: Unit | F3: Unit Cost (FY24 CONUS) | G3: Extended Cost | H3: UNIFORMAT II Lv2 | I3: Cost Basis / Notes
A4: 1. ARMORY VAULT CONVERSION - 28 Barracks Rooms to 14 Armory Vaults
A5: 4 | B5: Armory | C5: New vault doors/frames/locksets - GSA Class V, Hamilton CI-5 (4 armory hallway locations) | D5: 4 | E5: EA | F5: 14599.4 | G5: =D5*F5 | H5: C10 | I5: Hamilton CI-5 door + flange set: $10,143.40 | Prorated air freight (TQL Global, 5-door shipment CVG-OKA): $1,956.00 | Install labor (certified 2-person crew, OCONUS): $2,500.00 | Unit total: $14,599.40
A6: 8 | B6: Armory | C6: Structural walls to support vault doors, drop ceiling infrastructure | D6: 4 | E6: EA | F6: 15000 | G6: =D6*F6 | H6: C10 | I6: Reinforced masonry/concrete walls, headers, lintels for vault door support
A7: 5 | B7: Armory | C7: Remove 28 windows/frames and 2 exit doors/frames (30 openings total) | D7: 30 | E7: EA | F7: 500 | G7: =D7*F7 | H7: F20 | I7: Window and door removal incl frame, disposal
A8: 6 | B8: Armory | C8: CMU wall enclosures at 17 former window openings | D8: 17 | E8: EA | F8: 5000 | G8: =D8*F8 | H8: B20 | I8: CMU infill 5'x6' openings: block, mortar, rebar, tie-in to existing structure
A9: 6 | B9: Armory | C9: New weapons port issue windows - custom steel frame, ballistic rated (11 EA) | D9: 11 | E9: EA | F9: 3500 | G9: =D9*F9 | H9: B20 | I9: Custom fabricated steel-frame weapon issue port windows, installed
A10: 7 | B10: Armory | C10: Remove drop ceilings in all 28 armory rooms (6,270 SF) | D10: 6270 | E10: SF | F10: 4 | G10: =D10*F10 | H10: F20 | I10: Ceiling grid/tile removal, disposal
A11: 7 | B11: Armory | C11: Paint all armory interior walls - 28 rooms (6,270 SF) | D11: 6270 | E11: SF | F11: 4 | G11: =D11*F11 | H11: C30 | I11: Interior latex paint, wall prep
A12: 11 | B12: Armory | C12: Armory bathrooms: Remove CT floor/walls, refinish, paint - 11 bathrooms (~1,650 SF) | D12: 1650 | E12: SF | F12: 10 | G12: =D12*F12 | H12: C30 | I12: Ceramic tile removal, skim coat, paint, VCT. 11 baths x 150 SF
A13: 5 | B13: Armory | C13: Remove 11 bathroom fixture sets (toilet, tub, sink, accessories) | D13: 11 | E13: EA | F13: 2500 | G13: =D13*F13 | H13: F20 | I13: Full fixture removal, disconnect, disposal per set
A14: 12 | B14: Armory | C14: Cap plumbing lines - 11 armory bathrooms | D14: 11 | E14: EA | F14: 2000 | G14: =D14*F14 | H14: D20 | I14: Cap water supply/drainage, includes access and patching
A15: 13 | B15: Armory | C15: Adjust valves to limit deadlegs in capped armory plumbing lines | D15: 1 | E15: LS | F15: 10000 | G15: =D15*F15 | H15: D20 | I15: System-wide valve adjustment to prevent stagnation
A16: 10 | B16: Armory | C16: Realign all electrical/mechanical ceiling fixtures after ceiling removal - 28 rooms | D16: 28 | E16: EA | F16: 2000 | G16: =D16*F16 | H16: D30 | I16: Relocate/adjust HVAC diffusers, sprinklers, fire alarm, lighting per room
... A19: 15 | B19: Armory | C19: New metal shelves at 11 weapons issue port windows | D19: 11 | E19: EA | F19: 600 | G19: =D19*F19 | H19: E20 | I19: Stainless/galvanized steel shelf, brackets, fasteners
A20: 2. ARMORY EXTERIOR - Walkways, Landings, Concrete Pads
A21: 2 | B21: Armory Ext | C21: Extend backside walkways - concrete sidewalk, safety railings (~200 LF) | D21: 200 | E21: LF | F21: 200 | G21: =D21*F21 | H21: G20 | I21: Concrete sidewalk, railings, grading, landscaping
A22: 3 | B22: Armory Ext | C22: New exterior landing/walkway at 11 weapons issue port windows | D22: 11 | E22: EA | F22: 1400 | G22: =D22*F22 | H22: G20 | I22: Concrete landing pad ~100 SF each at 11 issue window locations
A23: 16 | B23: Armory Ext | C23: New exterior concrete pads at issue windows - civil (11 locations x 80 SF) | D23: 880 | E23: SF | F23: 14 | G23: =D23*F23 | H23: G20 | I23: Formed concrete pad, 4 inch, gravel base
A24: 3. GYM TO WORKSPACE CONVERSION - CLB-4 Commo Swing Space to 4th MarRegt Admin/Ops
A25: 1 | B25: Gym/Admin | C25: Gym hallway: Patch concrete baseboard/wall, paint interior, new VCT flooring | D25: 1 | E25: LS | F25: 5000 | G25: =D25*F25 | H25: C30 | I25: Minor patching, paint, and flooring in gym hallway
A26: 4. COMM ROOM & WEAPONS CLEANING AREA
A27: 17 | B27: Comm Room | C27: Add exhaust ventilation to new indoor weapons cleaning area | D27: 1 | E27: LS | F27: 15000 | G27: =D27*F27 | H27: D30 | I27: Exhaust fan, ductwork, exterior louver, controls for weapons cleaning fumes
A28: 18 | B28: Comm Room | C28: Rec Room: New COMM room 8'x10' w/ gypsum walls, VCT, paint; replace acoustical ceiling | D28: 1 | E28: LS | F28: 15000 | G28: =D28*F28 | H28: C10 | I28: New 80 SF room: partitions, door, ceiling, flooring, paint
A29: 20 | B29: Comm Room | C29: Rec Room: New electrical outlets and switches in COMM room | D29: 1 | E29: LS | F29: 8000 | G29: =D29*F29 | H29: D50 | I29: Outlets, switches, dedicated circuits for comm equipment
A30: 21 | B30: Comm Room | C30: Split A/C systems for telecom room and COMMSEC storage vault (2 EA) | D30: 2 | E30: EA | F30: 12000 | G30: =D30*F30 | H30: D30 | I30: Ductless mini-split A/C, dedicated cooling for telecom/COMMSEC spaces
A31: 5. ADMIN - Laundry Room Conversion to Administrative Workspace
A32: 22 | B32: Admin | C32: Adjust HVAC supply duct/diffusers and exhaust for admin use in laundry room | D32: 1 | E32: LS | F32: 8000 | G32: =D32*F32 | H32: D30 | I32: Reroute/adjust ductwork, diffusers, registers for office occupancy
A33: 23 | B33: Admin | C33: Cap water supply, drainage, floor drains for washers and utility sink; adjust valves | D33: 1 | E33: LS | F33: 5000 | G33: =D33*F33 | H33: D20 | I33: Cap and seal all laundry plumbing, reduce deadlegs
A34: 24 | B34: Admin | C34: Laundry Room: Repaint all interior walls, new VCT flooring (~300 SF) | D34: 300 | E34: SF | F34: 9 | G34: =D34*F34 | H34: C30 | I34: Interior paint + VCT: $4/SF paint + $5/SF VCT
A35: 25 | B35: Admin | C35: Remove dryer exhaust duct and cap wall vent | D35: 1 | E35: LS | F35: 1500 | G35: =D35*F35 | H35: F20 | I35: Duct removal, vent cap, patch and paint exterior/interior wall
A36: 6. BATHS TO OSS VAULT - Locker Rooms / Sauna / Steam Room to OSS w/ SIPR Network
A37: 26 | B37: Baths>OSS | C37: Demo CIP concrete walls in shower/locker/sauna areas for open floorplan | D37: 1 | E37: LS | F37: 30000 | G37: =D37*F37 | H37: F20 | I37: Structural demolition of CIP concrete walls - engineering assessment required for load-bearing
A38: 35 | B38: Baths>OSS | C38: Cut CIP wall for new door opening from showers to hallway | D38: 1 | E38: EA | F38: 5000 | G38: =D38*F38 | H38: F20 | I38: Saw-cut CIP wall, install new header/frame - structural engineering required
A39: 39 | B39: Baths>OSS | C39: Mens: Complete demo - toilet partitions, CT floor/walls, fixtures, lockers, ceiling, showers | D39: 1 | E39: LS | F39: 14000 | G39: =D39*F39 | H39: F20 | I39: Full gut: 2 toilets, 2 urinals, 2 sinks, 2 showers, partitions, lockers, tile, ceiling
A40: 40 | B40: Baths>OSS | C40: Womens: Complete demo - benches, showers, fixtures, CT floor/walls, partitions, ceiling | D40: 1 | E40: LS | F40: 12000 | G40: =D40*F40 | H40: F20 | I40: Full gut: 2 showers, 2 toilets, 2 sinks, partitions, tile, ceiling
A41: 30 | B41: Baths>OSS | C41: Sauna Room: Remove all wood seats/benches/ceiling/walls/flooring, brick enclosure, exhaust vents | D41: 1 | E41: LS | F41: 8000 | G41: =D41*F41 | H41: F20 | I41: Complete sauna strip-out to bare structure
A42: 43 | B42: Baths>OSS | C42: Steam Room: Remove ceramic tile walls, benches, flooring, door/frame | D42: 1 | E42: LS | F42: 6000 | G42: =D42*F42 | H42: F20 | I42: Complete steam room strip-out including tile and moisture barriers
A43: 27 | B43: Baths>OSS | C43: Mens: New ceiling, wall refinish/paint, level floor, VCT, plug drains (~398 SF) | D43: 398 | E43: SF | F43: 35 | G43: =D43*F43 | H43: C30 | I43: Full renovation finishes: ceiling grid/tile, wall prep/paint, floor leveling, VCT
A44: 28 | B44: Baths>OSS | C44: Womens: New lighting, VCT flooring, wall refinish/paint, new alum door/frame/lockset (~300 SF) | D44: 300 | E44: SF | F44: 32 | G44: =D44*F44 | H44: C30 | I44: Full renovation finishes + new aluminum entry door assembly
A45: 41 | B45: Baths>OSS | C45: Sauna Room: New VCT flooring, refinish concrete walls, new ceiling, entry door (~97 SF) | D45: 97 | E45: SF | F45: 28 | G45: =D45*F45 | H45: C30 | I45: Convert to admin space: floor, walls, ceiling, door
A46: 42 | B46: Baths>OSS | C46: Steam Room: New VCT flooring, refinish concrete walls, new ceiling, entry door (~124 SF) | D46: 124 | E46: SF | F46: 28 | G46: =D46*F46 | H46: C30 | I46: Convert to admin space: floor, walls, ceiling, door
A47: 31 | B47: Baths>OSS | C47: Fitness Room Vault: New security door/frame/lockset/closure (X-10 combination lock) | D47: 1 | E47: EA | F47: 4000 | G47: =D47*F47 | H47: C10 | I47: Heavy-duty security door with X-10 lock for COMMSEC storage
A48: 36 | B48: Baths>OSS | C48: Modify/cap/remove all plumbing - sauna, steam, mens/womens locker rooms | D48: 1 | E48: LS | F48: 18000 | G48: =D48*F48 | H48: D20 | I48: Full plumbing removal/capping across 4 wet areas
... A59: 64 | B59: Baths>OSS | C59: OSS Vault entrance: Structural reinforcement at CIP wall opening for vault door emplacement (steel header, threshold plate, anchor bolts into CIP wall) | D59: 1 | E59: LS | F59: 12000 | G59: =D59*F59 | H59: C10 | I59: Supplemental to Item 35 (CIP wall cut $5,000). Vault door ~900 lbs requires steel lintel, sill plate, and frame anchoring into existing CIP wall.
A60: 7. BUILDING GENERAL - Whole-Building Systems & Code Compliance
A61: 47 | B61: Bldg General | C61: Adjust mechanical components first floor (HVAC diffusers, sprinklers, fire alarms) for ceiling removal | D61: 1 | E61: LS | F61: 35000 | G61: =D61*F61 | H61: D30 | I61: First floor mechanical adjustment: sprinkler heads, diffusers, FA devices
A62: 48 | B62: Bldg General | C62: Replace air-cooled chillers (2 EA) and chilled water circulating pumps (2 EA) - END OF SERVICE LIFE | D62: 1 | E62: LS | F62: 500000 | G62: =D62*F62 | H62: D30 | I62: CRITICAL: Chillers 12+ yrs past service life. 2x 100-150 ton chillers + 2x CW pumps + controls. VERIFY tonnage with FEAD mech engineer.
A63: 49 | B63: Bldg General | C63: Test, Adjust, Balance (TAB) all duct HVAC systems throughout facility (all 4 floors) | D63: 1 | E63: LS | F63: 60000 | G63: =D63*F63 | H63: D30 | I63: Full building TAB per AABC/NEBB standards. VERIFY if scope is first floor only or whole building.
A64: 50 | B64: Bldg General | C64: Replace 4 fire hose cabinets in new armory spaces (recessed, stainless, w/ hose/extinguisher) | D64: 4 | E64: EA | F64: 2500 | G64: =D64*F64 | H64: D40 | I64: Recessed FHC per NFPA 10, stainless steel finish
A65: 51 | B65: Bldg General | C65: Add supplemental water fountains in new OSS/Admin areas (4 EA) | D65: 4 | E65: EA | F65: 5000 | G65: =D65*F65 | H65: D20 | I65: Wall-mounted water fountains, plumbing connection, ADA compliance
A66: 8. BUILDING TELECOM - Telecom Room, OSP & ISP Cabling per UFC 3-580-01
A67: 52 | B67: Telecom | C67: Demo existing TR - remove all existing racks, cabling, equipment, flooring, paint | D67: 1 | E67: LS | F67: 12000 | G67: =D67*F67 | H67: F20 | I67: Full TR strip-out for renovation
A68: 53 | B68: Telecom | C68: Construct new TR: raised floor, racks, UPS, patch panels, grounding, EPO, fire suppression, HVAC | D68: 1 | E68: LS | F68: 85000 | G68: =D68*F68 | H68: D50 | I68: Full TR build-out per UFC 3-580-01 and MCIPAC G6 policy
A69: 54 | B69: Telecom | C69: Install OSP fiber optic cable from nearest demarcation point to building TR | D69: 1 | E69: LS | F69: 15000 | G69: =D69*F69 | H69: D50 | I69: OSP fiber, conduit, hand-holes, termination
A70: 55 | B70: Telecom | C70: Install ISP horizontal cabling - 28 drops to new armory spaces, admin, OSS areas | D70: 28 | E70: EA | F70: 1200 | G70: =D70*F70 | H70: D50 | I70: Cat6A or OM3 fiber per MCIPAC G6 policy, conduit, termination
A71: 56 | B71: Telecom | C71: Remove existing ISP cabling throughout first floor | D71: 1 | E71: LS | F71: 4000 | G71: =D71*F71 | H71: F20 | I71: Removal of legacy cabling, conduit, boxes per demo scope
A72: 9. EXTERIOR - Covered Overhangs, Pavilion, Site Work
A73: 57 | B73: Exterior | C73: Tree removal at new exterior concrete pad locations (6 EA) | D73: 6 | E73: EA | F73: 1500 | G73: =D73*F73 | H73: G10 | I73: Tree removal and disposal, stump grinding
A74: 58 | B74: Exterior | C74: Steel-frame covered overhang at issue windows - 3 locations | D74: 3 | E74: EA | F74: 35000 | G74: =D74*F74 | H74: G20 | I74: Steel-frame canopy structure, metal roofing, concrete footings, per location
A75: 59 | B75: Exterior | C75: New outdoor pavilion - steel frame, metal roof, concrete slab (approx 20'x40') | D75: 1 | E75: LS | F75: 55000 | G75: =D75*F75 | H75: G20 | I75: Steel-frame pavilion: columns, roof, 800 SF concrete slab, perimeter drainage
A76: 60 | B76: Exterior | C76: Site drainage improvements at new concrete pad locations | D76: 1 | E76: LS | F76: 5000 | G76: =D76*F76 | H76: G20 | I76: French drains or surface grading at pad locations
A77: 10. RESTROOMS & MISCELLANEOUS
A78: 61 | B78: Rest/Misc | C78: Public restroom: New fixtures (2 toilets, 2 sinks, accessories) for general use area | D78: 1 | E78: LS | F78: 15000 | G78: =D78*F78 | H78: D20 | I78: Replace fixtures, handles, accessories - ADA compliance check
A79: 62 | B79: Rest/Misc | C79: New security door/frame/lockset for exterior storage (1 EA) | D79: 1 | E79: EA | F79: 6000 | G79: =D79*F79 | H79: C10 | I79: Heavy-duty exterior security door with lockset and door closer
A80: 11. HAZARDOUS MATERIALS - Asbestos Mastic Abatement (Bhate Environmental Associates, 19 Nov 2001)
A81: 65 | B81: Hazmat | C81: Asbestos mastic abatement - OSS full-gut areas (mens locker ~398 SF, womens ~300 SF, sauna ~97 SF, steam ~124 SF); cove base/kickboard removal triggers abatement of underlying H3 ACM mastic (15% Chrysotile) | D81: 234 | E81: LF | F81: 25 | G81: =D81*F81 | H81: F20 | I81: Bhate Survey 19 Nov 2001, H3: 15% Chrysotile mastic under kickboard, 8,392 LF building-wide. Scope-limited to OSS gut rooms only. Perimeter est from room SF. FEAD ENV/IH to field-verify LF and unit cost before construction.
A82: 66 | B82: Hazmat | C82: Asbestos mastic abatement - armory bathroom VCT/CT renovation (11 bathrooms, ~1,650 SF total); floor tile and wall base removal at wall junctions triggers abatement of underlying H3 ACM mastic (15% Chrysotile) | D82: 385 | E82: LF | F82: 25 | G82: =D82*F82 | H82: F20 | I82: Bhate Survey 19 Nov 2001, H3. Armory scope Item 11: CT floor/wall removal in 11 baths. VCT/CT installation requires cove base removal at perimeter. Perimeter est: 11 baths x ~35 LF avg = 385 LF. FEAD ENV/IH to field-verify.
A83: 67 | B83: Hazmat | C83: Asbestos mastic abatement - gym conversion (VCT 1,749 SF, est. 168 LF perimeter) and laundry/admin conversion (VCT 300 SF, est. 70 LF perimeter); new VCT installation at wall base triggers abatement of underlying H3 ACM mastic | D83: 238 | E83: LF | F83: 25 | G83: =D83*F83 | H83: F20 | I83: Bhate Survey 19 Nov 2001, H3. Scope Items 3B (gym VCT) and 24 (laundry VCT) require base removal at wall perimeter. Combined perimeter est 238 LF. FEAD ENV/IH to field-verify.
A85: TOTAL BASE DIRECT COST (FY24 CONUS) | G85: =SUM(G5:G83)

Sheet PARAMETERS
A1: SCH-1024 | COST ESTIMATE PARAMETERS | LEVEL 3 ROM | FY27 | PAX ID 387356 | Fi Web BU26PPE70M
A3: PROJECT IDENTIFICATION
A4: Estimate Title | B4: SCH-1024 | Repair MULTI PURPOSE BEQ/BOQ/CO HQS | C4: Text | D4: DD Form 1391 | PAX ID 387356 | Fi Web BU26PPE70M
A5: Building / Installation | B5: SCH-1024 | Camp Schwab, Okinawa, Japan | C5: Text | D5: MCIPAC G-F PPE
A6: Supported Units | B6: 3rd Marine Logistics Group / III MEF | C6: Text | D6: Primary supported units
A7: PAX ID | B7: 387356 | C7: ID | D7: PAX System
A8: Fi Web Project Number | B8: BU26PPE70M | C8: ID | D8: Fi Web confirmed
A9: iNFADS RPUID | B9: 148675 | C9: ID | D9: iNFADS Real Property record
A10: Primary Project CCN | B10: 14345 | C10: CCN | D10: iNFADS CCN 14345
A11: Total Building GSF | B11: 84861 | C11: SF | D11: iNFADS confirmed
A12: Plant Replacement Value (iNFADS) | B12: 96523347 | C12: $ | D12: iNFADS confirmed; UFC 3-701-01 w/Ch 7
A13: Estimate Date | B13: 29 Apr 2026 | C13: Date | D13: Date of estimate production
A14: Estimate Level | B14: Level 3 ROM | C14: Text | D14: UFS 3-740-05 (2 Feb 2026); for information only
A15: Delivery Method | B15: Design-Build (DB) | C15: Method | D15: UFC 3-730-01 (2024)
A17: COST INPUTS (yellow = user input; locked unless directed)
A18: Base Year | B18: 2024 | C18: FY | D18: FY24 CONUS base costs
A19: Target Fiscal Year | B19: 2027 | C19: FY | D19: FY27 construction start
A20: Area Cost Factor (ACF) | B20: 1.85 | C20: Multiplier | D20: UFC 3-701-01 w/Ch 7 (25 Jul 2025), Table 4-1 OCONUS Okinawa M67400-0004
A21: Escalation Rate (annual) | B21: 0.021 | C21: % | D21: OSD FY25 published rate, client confirmed
A22: Escalation Years | B22: 3 | C22: Years | D22: FY24 base to FY27 target
A23: General Requirements | B23: 0.1 | C23: % | D23: FSRM program-directed; UFS 3-740-05
A25: PAX ASSOCIATED COSTS (informational; applied by PAX at submission)
A26: Contingency | B26: 0.1 | C26: % | D26: FSRM program-directed; PAX-applied to items subtotal
A27: Supervision Inspection and Overhead (SIOH) | B27: 0.08 | C27: % | D27: OCONUS FSRM customer-directed (8.0%); PAX-applied
A28: Design-Build Design (DB) | B28: 0.04 | C28: % | D28: UFC 3-730-01 (2024); PAX-applied
A29: Planning and Design (P&D) | B29: 0.06 | C29: % | D29: NON ADD; informational only; does not roll into TPC
A31: DERIVED VALUES (live formulas; do not edit)
A32: Compound Escalation Factor | B32: =(1+B21)^B22 | C32: Factor | D32: (1 + escalation)^years
A33: Base Direct Cost (FY24 CONUS) | B33: =SCOPE_DETAIL!G85 | C33: $ | D33: Sum of all scope items on SCOPE_DETAIL
A34: Pre-Calibration Subtotal | B34: =B33*B20*B32*(1+B23) | C34: $ | D34: Base Direct x ACF x Escalation x (1 + General Requirements)
A35: Locked Total Project Cost | B35: 10413140 | C35: $ | D35: PAX-locked TPC; reconciliation target
A36: Items Subtotal Target (PAX paste) | B36: =B35/1.23552 | C36: $ | D36: Locked TPC / 1.23552 (1.10 x 1.08 x 1.04)
A37: Cost Adjustment Factor | B37: =B36/B34 | C37: Factor | D37: Items Subtotal Target / Pre-Calibration Subtotal; calibrates ROM chain to locked TPC
A39: PLANNING RATES
A40: JPY/USD Planning Rate | B40: 150.4415 | C40: Rate | D40: FY26 budget planning rate; H.10 live rate at PAX submission
A42: ACTIVE REFERENCES
A43: MCO 11000.5 (03 Jun 2016) | Real Property FSRM Program
A44: MCO 11000.12 (08 Sep 2014) | Real Property Facilities Manual
A45: Consistency Review Board Guidelines (May 2024, REV #15) | DD Form 1391 line-item sequencing
A46: UFC 3-701-01 with Change 7 (25 Jul 2025) | PUC, ACF, PRV authority
A47: UFC 3-730-01 (2024) | Design-Build contracting
A48: UFS 3-740-05 (02 Feb 2026) | Cost estimating ROM levels
A49: JED Cost Estimating Guidance (Combined, Nov 2025)
A50: Japan District Design Guide v9 (April 2025)
A51: 10 U.S.C. Section 2802 | DoD 4270.5-M | Classification of Work

Sheet DD1391_BLOCK9
A1: SCH-1024 | DD FORM 1391 BLOCK 9 - PAX PASTE | LEVEL 3 ROM | FY27 | PAX ID 387356 | Fi Web BU26PPE70M
A2: All amounts in $000s. Paste discipline rollups into PAX Block 9 items table; PAX-loaded Cont 10% / SIOH 8% / DB 4% render the printed Total Project Cost. P&D 6% NON ADD shown for visibility.
A3: Cost Element | B3: Amount ($000) | C3: Notes / UNIFORMAT
A4: B20 | Exterior Enclosure | B4: =ROUND( SUMIF(SCOPE_DETAIL!H:H,"B20",SCOPE_DETAIL!G:G) * (PARAMETERS!B34/PARAMETERS!B33) * PARAMETERS!B37 / 1000, 0) | C4: UNIFORMAT II Lv2 B20 rollup; absorbs base-cost adjustments via Cost Adjustment Factor
A5: C10 | Interior Construction | B5: =ROUND( SUMIF(SCOPE_DETAIL!H:H,"C10",SCOPE_DETAIL!G:G) * (PARAMETERS!B34/PARAMETERS!B33) * PARAMETERS!B37 / 1000, 0) | C5: UNIFORMAT II Lv2 C10 rollup; absorbs base-cost adjustments via Cost Adjustment Factor
A6: C30 | Interior Finishes | B6: =ROUND( SUMIF(SCOPE_DETAIL!H:H,"C30",SCOPE_DETAIL!G:G) * (PARAMETERS!B34/PARAMETERS!B33) * PARAMETERS!B37 / 1000, 0) | C6: UNIFORMAT II Lv2 C30 rollup; absorbs base-cost adjustments via Cost Adjustment Factor
A7: D20 | Plumbing | B7: =ROUND( SUMIF(SCOPE_DETAIL!H:H,"D20",SCOPE_DETAIL!G:G) * (PARAMETERS!B34/PARAMETERS!B33) * PARAMETERS!B37 / 1000, 0) | C7: UNIFORMAT II Lv2 D20 rollup; absorbs base-cost adjustments via Cost Adjustment Factor
A8: D30 | HVAC / Mechanical | B8: =ROUND( SUMIF(SCOPE_DETAIL!H:H,"D30",SCOPE_DETAIL!G:G) * (PARAMETERS!B34/PARAMETERS!B33) * PARAMETERS!B37 / 1000, 0) | C8: UNIFORMAT II Lv2 D30 rollup; absorbs base-cost adjustments via Cost Adjustment Factor
A9: D40 | Fire Protection | B9: =ROUND( SUMIF(SCOPE_DETAIL!H:H,"D40",SCOPE_DETAIL!G:G) * (PARAMETERS!B34/PARAMETERS!B33) * PARAMETERS!B37 / 1000, 0) | C9: UNIFORMAT II Lv2 D40 rollup; absorbs base-cost adjustments via Cost Adjustment Factor
A10: D50 | Electrical / Communications | B10: =ROUND( SUMIF(SCOPE_DETAIL!H:H,"D50",SCOPE_DETAIL!G:G) * (PARAMETERS!B34/PARAMETERS!B33) * PARAMETERS!B37 / 1000, 0) | C10: UNIFORMAT II Lv2 D50 rollup; absorbs base-cost adjustments via Cost Adjustment Factor
A11: E20 | Furnishings | B11: =ROUND( SUMIF(SCOPE_DETAIL!H:H,"E20",SCOPE_DETAIL!G:G) * (PARAMETERS!B34/PARAMETERS!B33) * PARAMETERS!B37 / 1000, 0) | C11: UNIFORMAT II Lv2 E20 rollup; absorbs base-cost adjustments via Cost Adjustment Factor
A12: F20 | Selective Demolition | B12: =ROUND( SUMIF(SCOPE_DETAIL!H:H,"F20",SCOPE_DETAIL!G:G) * (PARAMETERS!B34/PARAMETERS!B33) * PARAMETERS!B37 / 1000, 0) | C12: UNIFORMAT II Lv2 F20 rollup; absorbs base-cost adjustments via Cost Adjustment Factor
A13: G10 | Site Preparation | B13: =ROUND( SUMIF(SCOPE_DETAIL!H:H,"G10",SCOPE_DETAIL!G:G) * (PARAMETERS!B34/PARAMETERS!B33) * PARAMETERS!B37 / 1000, 0) | C13: UNIFORMAT II Lv2 G10 rollup; absorbs base-cost adjustments via Cost Adjustment Factor
A14: G20 | Site Improvements | B14: =ROUND( SUMIF(SCOPE_DETAIL!H:H,"G20",SCOPE_DETAIL!G:G) * (PARAMETERS!B34/PARAMETERS!B33) * PARAMETERS!B37 / 1000, 0) | C14: UNIFORMAT II Lv2 G20 rollup; absorbs base-cost adjustments via Cost Adjustment Factor
A15: ITEMS SUBTOTAL (PAX Block 9 paste total) | B15: =SUM(B4:B14) | C15: Sum of discipline rollups; this is the value pasted into PAX items table
A17: Contingency (10.0%) PAX-applied | B17: =B15*0.10 | C17: 10% of items subtotal; FSRM program-directed
A18: Total Contract Cost | B18: =B15*1.10 | C18: Items subtotal x 1.10
A19: SIOH (8.0%) PAX-applied | B19: =B15*1.10*0.08 | C19: 8% of TCC; OCONUS FSRM customer-directed
A20: Total Funded Cost | B20: =B15*1.10*1.08 | C20: TCC x 1.08
A21: DB Design (4.0%) PAX-applied | B21: =B15*1.10*1.08*0.04 | C21: 4% of TFC; UFC 3-730-01 (2024)
A22: TOTAL PROJECT COST | B22: =B15*1.23552 | C22: TFC x 1.04 = items subtotal x 1.23552
A23: TOTAL PROJECT COST ($000 rounded) | B23: =ROUND(B22,0) | C23: Printed TPC on DD Form 1391 face
A25: Planning and Design (6.0%) NON ADD | B25: =ROUND(B15*0.06,0) | C25: Informational; does not roll into TPC; PAX renders separately on form
A27: Reconciliation (must equal 0) | B27: =B23-ROUND(PARAMETERS!B35/1000,0) | C27: Printed TPC ($000) minus Locked TPC ($000)
A29: CLASSIFICATION OF WORK
A30: Construction | B30: =B23 | C30: 100% of Total Project Cost | 10 U.S.C. Section 2802
A31: Special Interest: Restoration and Modernization | B31: =B23 | C31: 100% SRM | MCO 11000.12 | DoD 4270.5-M
