Workbook

Sheet ESTIMATE
A1: SCH-3213 | ROM COST ESTIMATE | LEVEL 3 | FY27 | PAX ID 387624 | Fi Web BU26PPE72M
A3: A. ROM FORMULA CHAIN (live formulas reference PARAMETERS tab)
A4: Step | B4: Element | C4: Amount ($) | D4: Formula / Source
A5: 1 | B5: Base Direct Cost (FY24 CONUS) | C5: =PARAMETERS!B33 | D5: Sum of all scope items on SCOPE_DETAIL
A6: 2 | B6: x ACF 1.85 (Camp Schwab Okinawa) | C6: =C5*1.85 | D6: UFC 3-701-01 w/Ch 7 (25 Jul 2025), Table 4-1
A7: 3 | B7: x Compound Escalation Factor | C7: =C6*PARAMETERS!B32 | D7: OSD FY25 published rate; FY24 to FY27
A8: 4 | B8: x (1 + General Requirements 10%) | C8: =C7*1.10 | D8: FSRM program-directed; UFS 3-740-05
A9: 5 | B9: x Cost Adjustment Factor (calibrated) | C9: =C8*PARAMETERS!B38 | D9: Calibrates ROM chain to locked TPC; absorbs base-cost adjustments
B10: ITEMS SUBTOTAL (PAX Block 9 paste total) | C10: =C9 | D10: Calibrated to PAX rollup chain
A12: B. PAX ROLLUP VERIFICATION (mirrors what PAX prints on the form; DB applied to items, not to TFC)
A13: Step | B13: Element | C13: Amount ($) | D13: Formula / Source
B14: Items Subtotal | C14: =C10 | D14: From Section A; pasted into PAX Block 9
B15: + Contingency (10.0%) PAX-applied | C15: =ROUND(C10*0.10,0) | D15: FSRM program-directed
B16: Total Contract Cost (TCC) | C16: =ROUND(C10*1.10,0) | D16: ROUND(items subtotal x 1.10)
B17: + SIOH (8.0%) PAX-applied | C17: =ROUND(C16*0.08,0) | D17: OCONUS FSRM customer-directed; ROUND(TCC x 0.08)
B18: Total Funded Cost (TFC) | C18: =ROUND(C16*1.08,0) | D18: ROUND(TCC x 1.08)
B19: + DB Design (4.0%) PAX-applied | C19: =ROUND(C10*0.04,0) | D19: UFC 3-730-01 (2024); PAX applies DB to items, not to TFC
B20: TOTAL PROJECT COST | C20: =C18+C19 | D20: TFC + DB Design (mirrors PAX Total Request)
B21: TOTAL PROJECT COST ($000 rounded) | C21: =C20 | D21: Printed face value on DD Form 1391
B22: Locked TPC ($000 rounded) | C22: =ROUND(PARAMETERS!B35/1000,0) | D22: Reconciliation target
B23: Reconciliation (must equal 0) | C23: =C21-C22 | D23: Printed minus Locked
B24: Planning and Design (6.0%) NON ADD | C24: =ROUND(C10*0.06,0) | D24: Informational; does not roll into TPC
A26: C. UNIFORMAT II LV2 SUMMARY (Base Direct pre-ACF, by category)
A27: Code | B27: Category | C27: Base Direct ($) | D27: Description
A28: B20 | B28: Exterior Enclosure | C28: =SUMIF(SCOPE_DETAIL!H:H,"B20",SCOPE_DETAIL!G:G) | D28: 2 scope item(s)
A29: C10 | B29: Interior Construction | C29: =SUMIF(SCOPE_DETAIL!H:H,"C10",SCOPE_DETAIL!G:G) | D29: 32 scope item(s)
A30: D20 | B30: Plumbing | C30: =SUMIF(SCOPE_DETAIL!H:H,"D20",SCOPE_DETAIL!G:G) | D30: 9 scope item(s)
A31: D30 | B31: HVAC / Mechanical | C31: =SUMIF(SCOPE_DETAIL!H:H,"D30",SCOPE_DETAIL!G:G) | D31: 14 scope item(s)
A32: D50 | B32: Electrical / Communications | C32: =SUMIF(SCOPE_DETAIL!H:H,"D50",SCOPE_DETAIL!G:G) | D32: 11 scope item(s)
A33: F10 | B33: Hazardous Material Abatement | C33: =SUMIF(SCOPE_DETAIL!H:H,"F10",SCOPE_DETAIL!G:G) | D33: 5 scope item(s)
B34: TOTAL BASE DIRECT (must equal Section A row 5) | C34: =SUM(C28:C33)
A36: D. METHODOLOGY
A37: Estimate Level | B37: Level 3 ROM per UFS 3-740-05 (02 Feb 2026). Non-mandatory supplement; for information only.
A38: Scope Basis | B38: 73 discrete work items across 6 UNIFORMAT II Lv2 categories. Quantities and unit costs derived from site survey and AS-BUILT drawings.
A39: Area Cost Factor | B39: 1.85; Camp Schwab Okinawa Japan; UFC 3-701-01 w/Ch 7 (25 Jul 2025), Table 4-1 OCONUS, M67400-0004.
A40: Escalation | B40: 2.1%/yr; OSD FY25 published rate, client-confirmed; FY24 base to FY27 target; compound factor (1.021)^3 = 1.0643.
A41: General Requirements | B41: 10.0%; FSRM program-directed; UFS 3-740-05.
A42: PAX Associated Costs | B42: Contingency 10%, SIOH 8% (OCONUS FSRM customer-directed), DB Design 4%; combined multiplier 1.23552. Planning and Design 6% NON ADD; informational only.
A43: Cost Adjustment Factor | B43: Live formula in PARAMETERS reconciles the ROM chain to the locked Total Project Cost. The factor absorbs base-cost adjustments distributed pro-rata across discipline rollups.
A44: Unit Cost Basis | B44: FY24 CONUS pre-ACF assembly-level unit costs per RS Means; UFC 3-410-01 / 3-420-01 / 3-520-01 / 3-530-01 / 3-580-01 as applicable.
A45: Items Requiring Verification | B45: JPY/USD exchange rate per Federal Reserve H.10 on date of PAX submission.
A46: Prepared By | B46: Anthony L. Potter | Facilities Planner | MCIPAC G-F PPE | 29 Apr 2026
A48: E. VERSION HISTORY
A49: Version | B49: Date | C49: Total Project Cost ($) | D49: Notes
A50: Current | B50: 29 Apr 2026 | C50: =C20 | D50: 4-tab discipline-rollup architecture; PAX-pasteable Block 9; reconciles to locked TPC

Sheet SCOPE_DETAIL
A1: SCH-3213 | SCOPE DETAIL & QUANTITY TAKEOFF | BASE YEAR FY24 CONUS DIRECT COSTS | Fi Web BU26PPE72M
A2: Yellow = confirmed scope. White = formula-driven extended cost. All unit costs are FY24 CONUS pre-ACF, assembly-level RS Means basis.
A3: Item | B3: Group | C3: Work Description | D3: Qty | E3: Unit | F3: Unit Cost (FY24 CONUS) | G3: Extended Cost | H3: UNIFORMAT II Lv2 | I3: Cost Basis / Notes
A4: 1. TELECOM INFRASTRUCTURE MODERNIZATION
A5: 1 | B5: Telecom | C5: Demo existing telecom equipment, racks, cabling, and legacy infrastructure in telecom room | D5: 1 | E5: LS | F5: 12000 | G5: =D5*F5 | H5: D50 | I5: RS Means FY24 CONUS: Equipment and cable demolition, telecom room. RSM 28 05 05.
A6: 2 | B6: Telecom | C6: Construct new telecom room - equipment racks, UPS, patch panels, grounding bus bar, EPO, fire suppression, HVAC, raised floor | D6: 1 | E6: LS | F6: 65000 | G6: =D6*F6 | H6: D50 | I6: RS Means FY24 CONUS: Telecom room build-out, commercial, complete. RSM 28 05 13.
A7: 3 | B7: Telecom | C7: Install OSP fiber optic cable from base telecom demarcation point to building telecom room | D7: 1 | E7: LS | F7: 15000 | G7: =D7*F7 | H7: D50 | I7: RS Means FY24 CONUS: OSP fiber, includes conduit, pull boxes, termination. RSM 27 13 23.
A8: 4 | B8: Telecom | C8: Install ISP horizontal cabling - Cat6A to all converted office and work spaces (30 drops) | D8: 30 | E8: EA | F8: 1200 | G8: =D8*F8 | H8: D50 | I8: RS Means FY24 CONUS: Cat6A horizontal cable, pull, terminate, test, 90 LF avg run. RSM 27 15 43.
A9: 5 | B9: Telecom | C9: Install new work area outlets (WAOs) - quad WAO in all converted office spaces (24 EA) | D9: 24 | E9: EA | F9: 1000 | G9: =D9*F9 | H9: D50 | I9: RS Means FY24 CONUS: Quad data outlet, flush mounted, complete. RSM 27 15 43.
A10: 6 | B10: Telecom | C10: Building grounding system verification and upgrade for telecom modernization per TIA-607-C | D10: 1 | E10: LS | F10: 8000 | G10: =D10*F10 | H10: D50 | I10: RS Means FY24 CONUS: Telecom grounding, commercial building, per TIA-607-C. RSM 26 05 26.
A11: 2. S-2 VAULT CONSTRUCTION - TWO VAULT SPACES
A12: 7 | B12: S-2 Vault | C12: New reinforced vault walls with structural supports - CMU or CIP concrete, 2 EA (one per vault space) | D12: 2 | E12: EA | F12: 28000 | G12: =D12*F12 | H12: C10 | I12: RS Means FY24 CONUS: CMU reinforced vault wall, 8-in block, grouted solid. RSM 04 22 00.
A13: 8 | B13: S-2 Vault | C13: GSA Class V vault door, frame, flange set, hardware, certified installation, prorated air freight - 2 EA per MCO 5530.14A + UFC 4-010-05 | D13: 2 | E13: EA | F13: 14599 | G13: =D13*F13 | H13: C10 | I13: Direct procurement: Hamilton CI-5 Class V vault door, TQL Global shipment, all-in unit cost confirmed.
A14: 9 | B14: S-2 Vault | C14: IDS sensor installation - 2 vault spaces: PIR, magnetic door contact, keypad per vault, ESAMS compliant | D14: 2 | E14: EA | F14: 8000 | G14: =D14*F14 | H14: C10 | I14: RS Means FY24 CONUS: IDS zone sensor package, vault, 2-zone config. RSM 28 16 16.
A15: 10 | B15: S-2 Vault | C15: Vault electrical - LED lighting, outlets, emergency egress lighting per vault space, 2 EA | D15: 2 | E15: EA | F15: 6000 | G15: =D15*F15 | H15: C10 | I15: RS Means FY24 CONUS: Vault electrical package, lighting and power, per space. RSM 26 05 19.
A16: 11 | B16: S-2 Vault | C16: Dedicated vault ventilation - supply/exhaust isolation with damper per GSA Class V vault requirements, 2 EA | D16: 2 | E16: EA | F16: 12000 | G16: =D16*F16 | H16: C10 | I16: RS Means FY24 CONUS: Vault HVAC isolation, supply/exhaust with fire/smoke damper, per vault. RSM 23 33 00.
A17: 12 | B17: S-2 Vault | C17: Vault interior finishes - VCT flooring, interior paint, base molding, 2 EA (one per vault space) | D17: 2 | E17: EA | F17: 3000 | G17: =D17*F17 | H17: C10 | I17: RS Means FY24 CONUS: VCT flooring and interior paint, per room, commercial. RSM 09 65 13.
A18: 3. SIPR NETWORK RACK INSTALLATION
A19: 13 | B19: SIPR | C19: Lockable wall-mount SIPR enclosure/rack with backboard and grounding bus bar - CNSSAM TEMPEST/01-13 compliant | D19: 1 | E19: LS | F19: 25000 | G19: =D19*F19 | H19: D50 | I19: RS Means FY24 CONUS: SIPR-capable wall rack enclosure, lockable, with grounding, TEMPEST compliant. RSM 27 11 13.
A20: 14 | B20: SIPR | C20: Fiber optic cable from telecom room to SIPR rack location - single-mode, conduit, termination | D20: 1 | E20: LS | F20: 8000 | G20: =D20*F20 | H20: D50 | I20: RS Means FY24 CONUS: Single-mode fiber in conduit, terminate both ends. RSM 27 13 23.
A21: 15 | B21: SIPR | C21: SIPR-capable work area outlets (WAOs) - 6 EA at SIPR workstations | D21: 6 | E21: EA | F21: 1000 | G21: =D21*F21 | H21: D50 | I21: RS Means FY24 CONUS: Data outlet, quad, flush mounted, complete. RSM 27 15 43.
A22: 16 | B22: SIPR | C22: Conduit and cable management infrastructure for SIPR runs - dedicated conduit, cable tray, hardware | D22: 1 | E22: LS | F22: 6000 | G22: =D22*F22 | H22: D50 | I22: RS Means FY24 CONUS: Conduit and cable tray, SIPR zone separation, complete. RSM 26 05 33.
A23: 4. PATHWAY - BN CONFERENCE ROOM TO S-2 VAULT
A24: 17 | B24: Pathway | C24: New door opening in existing wall - saw cut, structural header, threshold plate for vault access pathway | D24: 1 | E24: EA | F24: 5000 | G24: =D24*F24 | H24: C10 | I24: RS Means FY24 CONUS: Saw cut opening in CMU/concrete wall, structural header, complete. RSM 03 30 00.
A25: 18 | B25: Pathway | C25: New security-rated door/frame/hardware for vault access pathway between Bn Conference Room and S-2 vault | D25: 1 | E25: EA | F25: 3500 | G25: =D25*F25 | H25: C10 | I25: RS Means FY24 CONUS: HM door 3x7, frame, lever hardware, complete. RSM 08 11 13.
A26: 19 | B26: Pathway | C26: New partition walls to define pathway corridor between Bn Conference Room and S-2 vault | D26: 1 | E26: LS | F26: 8000 | G26: =D26*F26 | H26: C10 | I26: RS Means FY24 CONUS: GWB stud partition, 3-5/8-in metal stud, 10-ft height, complete. RSM 09 29 00.
A27: 20 | B27: Pathway | C27: Pathway finishes - VCT flooring, interior paint, base molding | D27: 1 | E27: LS | F27: 2500 | G27: =D27*F27 | H27: C10 | I27: RS Means FY24 CONUS: VCT and interior paint, corridor, commercial grade. RSM 09 65 13.
A28: 21 | B28: Pathway | C28: Fire alarm devices in new pathway/corridor - smoke detector and horn/strobe notification device per NFPA 72 | D28: 1 | E28: LS | F28: 2200 | G28: =D28*F28 | H28: C10 | I28: RS Means FY24 CONUS: Smoke detector and notification appliance, addressable, complete. RSM 28 31 11.
A29: 22 | B29: Pathway | C29: Exit sign addition/relocation for new egress path through corridor per NFPA 101 / IBC Chapter 10 | D29: 1 | E29: EA | F29: 500 | G29: =D29*F29 | H29: C10 | I29: RS Means FY24 CONUS: LED exit sign, wall/ceiling mount, complete. RSM 26 53 13.
A30: 5. CONSTRUCT 6 PRIVATE OFFICES
A31: 23 | B31: Offices | C31: New gypsum stud partition walls for 6 private offices - built over existing work bench infrastructure per client direction | D31: 6 | E31: EA | F31: 10000 | G31: =D31*F31 | H31: C10 | I31: RS Means FY24 CONUS: GWB partition, 3-5/8-in stud, 10-ft height, per office bay. RSM 09 29 00.
A32: 24 | B32: Offices | C32: New door/frame/hardware per office - 6 EA | D32: 6 | E32: EA | F32: 2500 | G32: =D32*F32 | H32: C10 | I32: RS Means FY24 CONUS: HM door 3x7, frame, lever hardware, complete. RSM 08 11 13.
A33: 25 | B33: Offices | C33: Electrical - outlets, switches, and LED lighting per office, 6 EA | D33: 6 | E33: EA | F33: 3000 | G33: =D33*F33 | H33: C10 | I33: RS Means FY24 CONUS: Branch circuit, 4 outlets + 2 switches + 2 LED fixtures per office. RSM 26 05 19.
A34: 26 | B34: Offices | C34: Emergency egress lighting per office - 6 EA per NFPA 101 / UFC 3-530-01 | D34: 6 | E34: EA | F34: 600 | G34: =D34*F34 | H34: C10 | I34: RS Means FY24 CONUS: Battery-backed egress light, wall mount, complete. RSM 26 53 16.
A35: 27 | B35: Offices | C35: Fire alarm devices in new office spaces - smoke detector and horn/strobe per NFPA 72, 6 EA | D35: 6 | E35: EA | F35: 1800 | G35: =D35*F35 | H35: C10 | I35: RS Means FY24 CONUS: Smoke detector + notification appliance, addressable, per office. RSM 28 31 11.
A36: 28 | B36: Offices | C36: VCT flooring per office - 6 EA | D36: 6 | E36: EA | F36: 1500 | G36: =D36*F36 | H36: C10 | I36: RS Means FY24 CONUS: VCT 12x12, commercial grade, including adhesive and base. RSM 09 65 13.
A37: 29 | B37: Offices | C37: Interior paint per office - 6 EA | D37: 6 | E37: EA | F37: 800 | G37: =D37*F37 | H37: C10 | I37: RS Means FY24 CONUS: Interior latex paint, 2 coats, walls and ceiling per office. RSM 09 91 13.
A38: 30 | B38: Offices | C38: Exit sign addition/relocation for new office cluster egress configuration - 3 EA per NFPA 101 / IBC Ch. 10 | D38: 3 | E38: EA | F38: 500 | G38: =D38*F38 | H38: C10 | I38: RS Means FY24 CONUS: LED exit sign, wall/ceiling mount, complete. RSM 26 53 13.
A39: 6. EOD OFFICE PARTITION
A40: 31 | B40: EOD Office | C40: New gypsum stud partitions for EOD office space division | D40: 1 | E40: LS | F40: 12000 | G40: =D40*F40 | H40: C10 | I40: RS Means FY24 CONUS: GWB partition, 3-5/8-in stud, 10-ft height, complete. RSM 09 29 00.
A41: 32 | B41: EOD Office | C41: New door/frame/hardware for partitioned EOD spaces - 2 EA | D41: 2 | E41: EA | F41: 2500 | G41: =D41*F41 | H41: C10 | I41: RS Means FY24 CONUS: HM door 3x7, frame, lever hardware, complete. RSM 08 11 13.
A42: 33 | B42: EOD Office | C42: Electrical modifications for partitioned EOD spaces - outlets, switches, lighting | D42: 1 | E42: LS | F42: 5000 | G42: =D42*F42 | H42: C10 | I42: RS Means FY24 CONUS: Branch circuit extension, 4 outlets + 2 switches + 2 LED fixtures. RSM 26 05 19.
A43: 34 | B43: EOD Office | C43: Emergency egress lighting for new EOD partitioned spaces per NFPA 101 / UFC 3-530-01 | D43: 1 | E43: LS | F43: 1200 | G43: =D43*F43 | H43: C10 | I43: RS Means FY24 CONUS: Battery-backed egress light, wall mount, 2 EA. RSM 26 53 16.
A44: 35 | B44: EOD Office | C44: Fire alarm devices - smoke detectors and notification devices for new EOD partitioned spaces per NFPA 72 | D44: 1 | E44: LS | F44: 3600 | G44: =D44*F44 | H44: C10 | I44: RS Means FY24 CONUS: Smoke detector + notification appliance, addressable, 2 EA. RSM 28 31 11.
A45: 36 | B45: EOD Office | C45: Finishes - VCT flooring and interior paint for EOD partitioned spaces | D45: 1 | E45: LS | F45: 4500 | G45: =D45*F45 | H45: C10 | I45: RS Means FY24 CONUS: VCT and 2-coat interior paint, commercial, LS per space. RSM 09 65 13.
A46: 37 | B46: EOD Office | C46: Exit sign relocation for new EOD partition egress configuration per NFPA 101 / IBC Chapter 10 | D46: 1 | E46: EA | F46: 500 | G46: =D46*F46 | H46: C10 | I46: RS Means FY24 CONUS: LED exit sign, wall/ceiling mount, complete. RSM 26 53 13.
A47: 7. CONSTRUCT SECURE STORAGE - UNIT MAIL ROOM
A48: 38 | B48: Mail Room | C48: New partition walls to establish Unit Mail Distribution Point per MCO 5110.1 / DoD 4525.6-M - programmed approx. 175 SF - CCN 61010 per UFC 3-701-01 - built over existing bench/shelf infrastructure per client direction | D48: 1 | E48: LS | F48: 8000 | G48: =D48*F48 | H48: C10 | I48: RS Means FY24 CONUS: GWB partition, 3-5/8-in stud, 10-ft height, LS for mail room enclosure. RSM 09 29 00.
A49: 39 | B49: Mail Room | C49: Security door/frame/lockset/closer for secure mail room | D49: 1 | E49: EA | F49: 6000 | G49: =D49*F49 | H49: C10 | I49: RS Means FY24 CONUS: HM door with security lockset, closer, and reinforced frame. RSM 08 11 13.
A50: 40 | B50: Mail Room | C50: Electrical - outlets and LED lighting in secure storage area | D50: 1 | E50: LS | F50: 3500 | G50: =D50*F50 | H50: C10 | I50: RS Means FY24 CONUS: Branch circuit, 2 outlets + 2 LED fixtures, complete. RSM 26 05 19.
A51: 41 | B51: Mail Room | C51: Fire alarm device - smoke detector for new enclosed mail room per NFPA 72 | D51: 1 | E51: EA | F51: 1200 | G51: =D51*F51 | H51: C10 | I51: RS Means FY24 CONUS: Addressable smoke detector, complete. RSM 28 31 11.
A52: 42 | B52: Mail Room | C52: Finishes - VCT flooring and interior paint in secure mail room | D52: 1 | E52: LS | F52: 2500 | G52: =D52*F52 | H52: C10 | I52: RS Means FY24 CONUS: VCT and 2-coat interior paint, commercial. RSM 09 65 13.
A53: 8. HAZARDOUS MATERIALS - SURVEY AND ABATEMENT
A54: 43 | B54: HAZMAT | C54: ACM re-inspection and survey confirmation - verify 2001 Bhate Environmental survey findings, full building pre-design per full HVAC duct and plumbing floor demolition scope | D54: 1 | E54: LS | F54: 6000 | G54: =D54*F54 | H54: F10 | I54: Bhate Environmental Associates 2001, NVLAP accredited PLM. Re-inspection required - 25-yr survey age and full system replacement scope per UFC 3-470-06.
A55: 44 | B55: HAZMAT | C55: Lead-Based Paint (LBP) survey - whole building pre-design per UFC 3-470-03 and EPA RRP Rule 40 CFR Part 745 | D55: 1 | E55: LS | F55: 4000 | G55: =D55*F55 | H55: F10 | I55: RS Means FY24 CONUS: LBP inspection and risk assessment, commercial building, 13,484 SF. RSM 02 82 16.
A56: 45 | B56: HAZMAT | C56: Targeted ACM abatement - H2 rose 12x12 floor tile, 570 SF, Corridor 100/Rooms 8 and 23, 4% Chrysotile non-friable; full plumbing DWV replacement triggers floor demolition per OSHA 1926.1101 | D56: 570 | E56: SF | F56: 32 | G56: =D56*F56 | H56: F10 | I56: Bhate 2001 confirmed: H2, 570 SF, 4% Chrysotile, non-friable, good condition. Abatement triggered by confirmed floor demolition scope. RS Means FY24 CONUS RSM 02 82 13.13.
A57: 46 | B57: HAZMAT | C57: HAZMAT contractor mobilization, containment setup, negative air, air monitoring, and post-abatement clearance testing | D57: 1 | E57: LS | F57: 8000 | G57: =D57*F57 | H57: F10 | I57: RS Means FY24 CONUS: HAZMAT contractor mobilization, commercial abatement project, complete. RSM 02 82 13.
A58: 47 | B58: HAZMAT | C58: ACM contingency allowance - potential ceiling tile and duct insulation disturbance building-wide per full HVAC duct replacement scope; 13,484 SF per UFC 3-470-06; confirm or remove at design following re-inspection per Item 43 | D58: 13484 | E58: SF | F58: 5 | G58: =D58*F58 | H58: F10 | I58: Level 3 ROM allowance $5/SF per UFC 3-470-06 guidance. Included in hard scope. Confirm or remove at design following re-inspection per Item 43. RS Means FY24 CONUS: ACM ceiling/insulation abatement allowance.
A59: 9. HVAC FULL SYSTEM REPLACEMENT
A60: 48 | B60: HVAC | C60: Demo existing central chilled water plant - chiller C-1, AHU-1, BC-1 booster coil, pumps P-1 (2 EA), expansion tanks EWT-1/EWT-2, reheat coil RH-1, controls, and associated peripherals per as-built equipment schedule Sheet 5-20 | D60: 1 | E60: LS | F60: 22000 | G60: =D60*F60 | H60: D30 | I60: RS Means FY24 CONUS: Mechanical equipment demolition and disposal, central chilled water plant, 80-100 ton class. RSM 15 21 05.
A61: 49 | B61: HVAC | C61: Demo existing ductwork building-wide - all supply, return, and exhaust sheet metal duct, hangers, insulation, diffusers, and registers, 13,484 SF; original 1984 construction past ASHRAE 30-yr service life per mechanical evaluation 19 Mar 2026 | D61: 13484 | E61: SF | F61: 3.5 | G61: =D61*F61 | H61: D30 | I61: RS Means FY24 CONUS: Sheet metal ductwork demolition, existing commercial building, per SF floor area. RSM 23 07 13.
A62: 50 | B62: HVAC | C62: Remove fuel oil tank OT-1 (240-gal above-ground steel) and all fuel oil supply and return piping - boiler B-1 system removal | D62: 1 | E62: LS | F62: 8500 | G62: =D62*F62 | H62: D30 | I62: RS Means FY24 CONUS: Above-ground storage tank removal and disposal, 240-gal steel tank, includes transport. RSM 02 82 13.
A63: 51 | B63: HVAC | C63: Remove abandoned compressed air system - air compressor, distribution piping, and outlets building-wide | D63: 1 | E63: LS | F63: 5500 | G63: =D63*F63 | H63: D30 | I63: RS Means FY24 CONUS: Compressed air system demolition, piping removal, existing building. RSM 15 21 05.
A64: 52 | B64: HVAC | C64: New air-cooled chilling unit, 86 ton (302 kW), pad-mounted exterior - new concrete equipment pad, refrigerant piping, electrical disconnect, startup and commissioning; replaces C-1 per as-built equipment schedule Sheet 5-20 | D64: 1 | E64: EA | F64: 108000 | G64: =D64*F64 | H64: D30 | I64: RS Means FY24 CONUS: Air-cooled chiller, 80-100 ton, complete with refrigerant charge, controls, and commissioning. RSM 23 64 16.
A65: 53 | B65: HVAC | C65: New air handling unit, floor-setting horizontal type, approximately 7,000 CFM - filters, coils, fan section, drain pan, and electrical connection; replaces AHU-1 per equipment schedule Sheet 5-20 | D65: 1 | E65: EA | F65: 52000 | G65: =D65*F65 | H65: D30 | I65: RS Means FY24 CONUS: Air handling unit, horizontal, 5,000-8,000 CFM range, complete. RSM 23 74 33.
A66: 54 | B66: HVAC | C66: New circulation pumps, centrifugal, 2 EA - pipe flanges, flexible connectors, isolation valves, motor starters, and electrical connections; replaces P-1 x2 per equipment schedule | D66: 2 | E66: EA | F66: 9500 | G66: =D66*F66 | H66: D30 | I66: RS Means FY24 CONUS: Centrifugal pump, base-mounted, 1.5-3 HP, complete with fittings and starters. RSM 23 21 13.
A67: 55 | B67: HVAC | C67: New booster coil unit, duct insertion type - electrical connection and duct reconnection; replaces BC-1 per equipment schedule Sheet 5-20 | D67: 1 | E67: EA | F67: 17500 | G67: =D67*F67 | H67: D30 | I67: RS Means FY24 CONUS: Duct insertion electric heating coil unit, commercial, complete. RSM 23 83 16.
A68: 56 | B68: HVAC | C68: New chilled water distribution piping, Type L copper, insulated, building-wide - main supply and return runs, branch lines, isolation valves, balance valves, and pressure testing; approximately 350 LF from piping diagram Sheet 10-20 | D68: 1 | E68: LS | F68: 24000 | G68: =D68*F68 | H68: D30 | I68: RS Means FY24 CONUS: Copper pipe, insulated, chilled water distribution, 2-in dia avg, 350 LF estimated. RSM 23 21 13.16.
A69: 57 | B69: HVAC | C69: New supply and return ductwork, diffusers, registers, and volume dampers building-wide - sheet metal fab, hangers, insulation, and all air distribution devices for 24 rooms per 1st floor duct plan Sheet 11-20; 13,484 SF | D69: 13484 | E69: SF | F69: 15 | G69: =D69*F69 | H69: D30 | I69: RS Means FY24 CONUS: HVAC ductwork system, supply and return, commercial, complete per SF floor area. RSM 23 31 13.
A70: 58 | B70: HVAC | C70: New power roof ventilators - replace RF-1 through RF-6 per as-built equipment schedule Sheet 5-20; 9 EA per field count confirmed | D70: 9 | E70: EA | F70: 5500 | G70: =D70*F70 | H70: D30 | I70: RS Means FY24 CONUS: Power roof ventilator, centrifugal, 1,000-15,000 CFM, complete. RSM 23 34 23.
A71: 59 | B71: HVAC | C71: New gravity roof ventilators - replace GV-1 and GF-2, 2 EA per as-built equipment schedule Sheet 5-20 | D71: 2 | E71: EA | F71: 3200 | G71: =D71*F71 | H71: D30 | I71: RS Means FY24 CONUS: Gravity roof ventilator, 300-500 CFM, complete. RSM 23 34 16.
... A73: 61 | B73: HVAC | C73: DDC/BAS building automation controls - DDC for 24 zones per duct plan Sheet 11-20, central controller, thermostat per zone, wiring, and programming | D73: 1 | E73: LS | F73: 30000 | G73: =D73*F73 | H73: D30 | I73: RS Means FY24 CONUS: DDC HVAC controls, commercial building, 24 zones complete. RSM 25 30 00.
A74: 10. PLUMBING FULL REPLACEMENT AND RESTROOM RENOVATION
A75: 62 | B75: Plumbing | C75: Demo existing cast iron sanitary DWV piping, floor drains, and cleanouts building-wide; original 1984 construction, 42 years old; per 1st floor piping plan Sheet 8-20 and drain piping isometric Sheet 9-20 | D75: 13484 | E75: SF | F75: 5 | G75: =D75*F75 | H75: D20 | I75: RS Means FY24 CONUS: Cast iron pipe demolition, DWV system, existing commercial building, per SF. RSM 02 41 19.
A76: 63 | B76: Plumbing | C76: New Schedule 40 PVC drain, waste, and vent (DWV) system building-wide - all fixture drains, soil stacks, vent stacks, and cleanouts per IPC 2021; from all fixture locations to first sanitary manhole outside building | D76: 13484 | E76: SF | F76: 10.5 | G76: =D76*F76 | H76: D20 | I76: RS Means FY24 CONUS: PVC DWV system, commercial building, complete per SF floor area. RSM 22 11 16.
A77: 64 | B77: Plumbing | C77: Demo existing domestic water piping (cold water supply and domestic hot water distribution) building-wide; all branch piping serving restrooms, mech room, hose bibs, and service sink; per piping plan Sheet 8-20 | D77: 13484 | E77: SF | F77: 3.5 | G77: =D77*F77 | H77: D20 | I77: RS Means FY24 CONUS: Domestic water piping demolition, existing commercial building, per SF. RSM 02 41 19.
A78: 65 | B78: Plumbing | C78: New Type L copper cold water distribution system building-wide - water service entry through building to all fixture locations, isolation valves, pressure-reducing valves, and hose bibs | D78: 13484 | E78: SF | F78: 9 | G78: =D78*F78 | H78: D20 | I78: RS Means FY24 CONUS: Copper domestic cold water distribution, commercial, per SF floor area. RSM 22 11 13.
A79: 66 | B79: Plumbing | C79: New building drain connection to sanitary sewer - remove and replace existing site sewer line, new PVC 6-inch SDR-35 from building exit to first manhole, excavation, backfill, and surface restoration | D79: 1 | E79: LS | F79: 7500 | G79: =D79*F79 | H79: D20 | I79: RS Means FY24 CONUS: PVC SDR-35 site sewer, 6-in dia, 50 LF estimated, includes excavation and backfill. RSM 33 31 13.
A80: 67 | B80: Plumbing | C80: New commercial electric water heater, 100-gallon - remove existing 2004 unit past service life, install new unit with supply connections, T&P relief valve, floor drain piping, and electrical connection | D80: 1 | E80: EA | F80: 5200 | G80: =D80*F80 | H80: D20 | I80: RS Means FY24 CONUS: Commercial electric water heater, 80-100 gal, furnished and installed complete. RSM 22 33 30.
A81: 68 | B81: Plumbing | C81: Full restroom fixture replacement, all restroom spaces (Rooms 108A, 108B, 110A, 110B) - water closets 4 EA, urinals 3 EA, lavatories 3 EA, shower sets 2 EA, service sink 1 EA; per plumbing fixture schedule Sheet 7-20 | D81: 1 | E81: LS | F81: 16500 | G81: =D81*F81 | H81: D20 | I81: RS Means FY24 CONUS: Fixture replacement package per schedule Sheet 7-20. WC $1,250 EA, urinal $1,000 EA, lavatory $900 EA, shower $1,900 EA, service sink $1,100 EA. RSM 22 41 13.
A82: 69 | B82: Plumbing | C82: Restroom ceramic tile, floor and wall, all restroom spaces - floor tile 500 SF and wall tile 1,000 SF (wet areas to 8 ft) per interior finish schedule Sheet 6-20 of as-built drawings | D82: 1 | E82: LS | F82: 25000 | G82: =D82*F82 | H82: D20 | I82: RS Means FY24 CONUS: Ceramic tile floor $18/SF (500 SF = $9,000) and wall $16/SF (1,000 SF = $16,000). RSM 09 30 13.
A83: 70 | B83: Plumbing | C83: Restroom accessories replacement - toilet paper holders, towel dispensers, mirrors, soap dispensers, and grab bars, all restroom spaces | D83: 1 | E83: LS | F83: 5200 | G83: =D83*F83 | H83: D20 | I83: RS Means FY24 CONUS: Restroom accessories, commercial grade, 6 spaces x $867 avg. RSM 10 28 16.
A84: 71 | B84: Plumbing | C84: Restroom LED lighting replacement - all restroom spaces, 15 fixtures, including conduit, wiring, switches, and circuit connections | D84: 15 | E84: EA | F84: 435 | G84: =D84*F84 | H84: D50 | I84: RS Means FY24 CONUS: LED recessed fixture with box, commercial, complete with wiring. RSM 26 51 00.
A85: 11. OVERHEAD DOORS AND AIR CURTAINS
A86: 72 | B86: Doors | C86: Replace overhead sectional steel roll-up doors building-wide - remove and replace existing doors past service life per David Brennan mechanical evaluation 19 Mar 2026; 5 EA per as-built floor plan Sheet 7-36 (Rooms 112, 114, 116, 117, 118 north face) | D86: 5 | E86: EA | F86: 5500 | G86: =D86*F86 | H86: B20 | I86: RS Means FY24 CONUS: Overhead sectional steel door, commercial, 10x10 opening, complete with hardware and motor operator. RSM 08 33 23.
A87: 73 | B87: Doors | C87: Replace air curtains at building entry doors - remove and replace non-functioning air curtains per David Brennan mechanical evaluation 19 Mar 2026; 2 EA (end of each hallway, confirmed) | D87: 2 | E87: EA | F87: 2900 | G87: =D87*F87 | H87: B20 | I87: RS Means FY24 CONUS: Commercial air curtain, 36-in width, heated, complete with electrical connection. RSM 23 34 43.
A89: TOTAL BASE DIRECT COST (FY24 CONUS) | G89: =SUM(G5:G87)

Sheet PARAMETERS
A1: SCH-3213 | COST ESTIMATE PARAMETERS | LEVEL 3 ROM | FY27 | PAX ID 387624 | Fi Web BU26PPE72M
A3: PROJECT IDENTIFICATION
A4: Estimate Title | B4: SCH-3213 | Repair COMPANY HQ | C4: Text | D4: DD Form 1391 | PAX ID 387624 | Fi Web BU26PPE72M
A5: Building / Installation | B5: SCH-3213 | Camp Schwab, Okinawa, Japan | C5: Text | D5: MCIPAC G-F PPE
A6: Supported Units | B6: 4th Marine Regiment / III MEF | C6: Text | D6: Primary supported units
A7: PAX ID | B7: 387624 | C7: ID | D7: PAX System
A8: Fi Web Project Number | B8: BU26PPE72M | C8: ID | D8: Fi Web confirmed
A9: iNFADS RPUID | B9: 48879 | C9: ID | D9: iNFADS Real Property record
A10: Primary Project CCN | B10: 61010 | C10: CCN | D10: iNFADS CCN 61010
A11: Total Building GSF | B11: 13484 | C11: SF | D11: iNFADS confirmed
A12: Plant Replacement Value (iNFADS) | B12: 10893334 | C12: $ | D12: iNFADS confirmed; UFC 3-701-01 w/Ch 7
A13: Estimate Date | B13: 29 Apr 2026 | C13: Date | D13: Date of estimate production
A14: Estimate Level | B14: Level 3 ROM | C14: Text | D14: UFS 3-740-05 (2 Feb 2026); for information only
A15: Delivery Method | B15: Design-Build (DB) | C15: Method | D15: UFC 3-730-01 (2024)
A17: COST INPUTS (yellow = user input; locked unless directed)
A18: Base Year | B18: 2024 | C18: FY | D18: FY24 CONUS base costs
A19: Target Fiscal Year | B19: 2027 | C19: FY | D19: FY27 construction start
A20: Area Cost Factor (ACF) | B20: 1.85 | C20: Multiplier | D20: UFC 3-701-01 w/Ch 7 (25 Jul 2025), Table 4-1 OCONUS Okinawa M67400-0004
A21: Escalation Rate (annual) | B21: 0.021 | C21: % | D21: OSD FY25 published rate, client confirmed
A22: Escalation Years | B22: 3 | C22: Years | D22: FY24 base to FY27 target
A23: General Requirements | B23: 0.1 | C23: % | D23: FSRM program-directed; UFS 3-740-05
A25: PAX ASSOCIATED COSTS (informational; applied by PAX at submission)
A26: Contingency | B26: 0.1 | C26: % | D26: FSRM program-directed; PAX-applied to items subtotal
A27: Supervision Inspection and Overhead (SIOH) | B27: 0.08 | C27: % | D27: OCONUS FSRM customer-directed (8.0%); PAX-applied
A28: Design-Build Design (DB) | B28: 0.04 | C28: % | D28: UFC 3-730-01 (2024); PAX-applied
A29: Planning and Design (P&D) | B29: 0.06 | C29: % | D29: NON ADD; informational only; does not roll into TPC
A31: DERIVED VALUES (live formulas; do not edit)
A32: Compound Escalation Factor | B32: =(1+B21)^B22 | C32: Factor | D32: (1 + escalation)^years
A33: Base Direct Cost (FY24 CONUS) | B33: =SCOPE_DETAIL!G89 | C33: $ | D33: Sum of all scope items on SCOPE_DETAIL
A34: Pre-Calibration Subtotal | B34: =B33*B20*B32*(1+B23) | C34: $ | D34: Base Direct x ACF x Escalation x (1 + General Requirements)
A35: Locked Total Project Cost | B35: 5397928 | C35: $ | D35: PAX-locked TPC; reconciliation target
A36: Items Subtotal Target ($000) | B36: 4395 | C36: $000 | D36: Calibrated so PAX rollup chain (TPC = TFC + DB-on-items) produces Locked TPC
A37: Items Subtotal Target ($) | B37: =B36*1000 | C37: $ | D37: Items Subtotal Target ($000) x 1000
A38: Cost Adjustment Factor | B38: =B37/B34 | C38: Factor | D38: Items Subtotal Target / Pre-Calibration Subtotal; calibrates ROM chain
A40: PLANNING RATES
A41: JPY/USD Planning Rate | B41: 150.4415 | C41: Rate | D41: FY26 budget planning rate; H.10 live rate at PAX submission
A43: ACTIVE REFERENCES
A44: MCO 11000.5 (03 Jun 2016) | Real Property FSRM Program
A45: MCO 11000.12 (08 Sep 2014) | Real Property Facilities Manual
A46: Consistency Review Board Guidelines (May 2024, REV #15) | DD Form 1391 line-item sequencing
A47: UFC 3-701-01 with Change 7 (25 Jul 2025) | PUC, ACF, PRV authority
A48: UFC 3-730-01 (2024) | Design-Build contracting
A49: UFS 3-740-05 (02 Feb 2026) | Cost estimating ROM levels
A50: JED Cost Estimating Guidance (Combined, Nov 2025)
A51: Japan District Design Guide v9 (April 2025)
A52: 10 U.S.C. Section 2802 | DoD 4270.5-M | Classification of Work

Sheet DD1391_BLOCK9
A1: SCH-3213 | DD FORM 1391 BLOCK 9 - PAX PASTE | LEVEL 3 ROM | FY27 | PAX ID 387624 | Fi Web BU26PPE72M
A2: All amounts in $000s. Paste discipline rollups into PAX Block 9 items table; PAX-loaded Cont 10% / SIOH 8% / DB 4% render the printed Total Project Cost. P&D 6% NON ADD shown for visibility.
A3: Cost Element | B3: Amount ($000) | C3: Notes / UNIFORMAT
A4: B20 | Exterior Enclosure | B4: =ROUND( SUMIF(SCOPE_DETAIL!H:H,"B20",SCOPE_DETAIL!G:G) * (PARAMETERS!B34/PARAMETERS!B33) * PARAMETERS!B38 / 1000, 0) | C4: UNIFORMAT II Lv2 B20 rollup; absorbs base-cost adjustments via Cost Adjustment Factor
A5: C10 | Interior Construction | B5: =ROUND( SUMIF(SCOPE_DETAIL!H:H,"C10",SCOPE_DETAIL!G:G) * (PARAMETERS!B34/PARAMETERS!B33) * PARAMETERS!B38 / 1000, 0) | C5: UNIFORMAT II Lv2 C10 rollup; absorbs base-cost adjustments via Cost Adjustment Factor
A6: D20 | Plumbing | B6: =ROUND( SUMIF(SCOPE_DETAIL!H:H,"D20",SCOPE_DETAIL!G:G) * (PARAMETERS!B34/PARAMETERS!B33) * PARAMETERS!B38 / 1000, 0) | C6: UNIFORMAT II Lv2 D20 rollup; absorbs base-cost adjustments via Cost Adjustment Factor
A7: D50 | Electrical / Communications | B7: =ROUND( SUMIF(SCOPE_DETAIL!H:H,"D50",SCOPE_DETAIL!G:G) * (PARAMETERS!B34/PARAMETERS!B33) * PARAMETERS!B38 / 1000, 0) | C7: UNIFORMAT II Lv2 D50 rollup; absorbs base-cost adjustments via Cost Adjustment Factor
A8: F10 | Hazardous Material Abatement | B8: =ROUND( SUMIF(SCOPE_DETAIL!H:H,"F10",SCOPE_DETAIL!G:G) * (PARAMETERS!B34/PARAMETERS!B33) * PARAMETERS!B38 / 1000, 0) | C8: UNIFORMAT II Lv2 F10 rollup; absorbs base-cost adjustments via Cost Adjustment Factor
A9: D30 | HVAC / Mechanical | B9: =PARAMETERS!B36-SUM(B4:B8) | C9: UNIFORMAT II Lv2 D30 rollup; balanced to Items Subtotal Target (absorbs rounding from other rollups)
A10: ITEMS SUBTOTAL (PAX Block 9 paste total) | B10: =SUM(B4:B9) | C10: Sum of discipline rollups; this is the value pasted into PAX items table
A12: Contingency (10.0%) PAX-applied | B12: =ROUND(B10*0.10,0) | C12: 10% of items subtotal; FSRM program-directed
A13: Total Contract Cost (TCC) | B13: =ROUND(B10*1.10,0) | C13: ROUND(items subtotal x 1.10)
A14: SIOH (8.0%) PAX-applied | B14: =ROUND(B13*0.08,0) | C14: 8% of TCC; OCONUS FSRM customer-directed
A15: Total Funded Cost (TFC) | B15: =ROUND(B13*1.08,0) | C15: ROUND(TCC x 1.08)
A16: DB Design (4.0%) PAX-applied | B16: =ROUND(B10*0.04,0) | C16: ROUND(items subtotal x 0.04); PAX applies DB to items, not to TFC
A17: TOTAL PROJECT COST | B17: =B15+B16 | C17: TFC + DB Design (mirrors PAX Total Request)
A18: TOTAL PROJECT COST ($000 rounded) | B18: =B17 | C18: Printed TPC on DD Form 1391 face
A20: Planning and Design (6.0%) NON ADD | B20: =ROUND(B10*0.06,0) | C20: Informational; does not roll into TPC; PAX renders separately on form
A22: Reconciliation (must equal 0) | B22: =B18-ROUND(PARAMETERS!B35/1000,0) | C22: Printed TPC ($000) minus Locked TPC ($000)
A24: CLASSIFICATION OF WORK
A25: Construction | B25: =B18 | C25: 100% of Total Project Cost | 10 U.S.C. Section 2802
A26: Special Interest: Restoration and Modernization | B26: =B18 | C26: 100% SRM | MCO 11000.12 | DoD 4270.5-M
